Metadata-Version: 1.0
Name: humdrum
Version: 0.7
Summary: A  CLI tool for youtube data api v3
Home-page: https://github.com/princekrroshan01/humdrum
Author: Prince Roshan
Author-email: princekrroshan01@gmail.com
License: MIT
Platform: UNKNOWN
